{
    "Pos": "TE",
    "1970": {
        "Tm": "DEN",
        "Pos": "TE",
        "Age": "26.0",
        "G": "14.0",
        "GS": "2.0",
        "Rec": "9.0",
        "PassingYds": "0.0",
        "PassingTD": "0.0",
        "PassingAtt": "0.0",
        "RushingYds": "0.0",
        "RushingTD": "0.0",
        "RushingAtt": "0.0",
        "ReceivingYds": "83.0",
        "ReceivingTD": "2.0",
        "FantasyPoints": "29.3",
        "Int": "0.0",
        "Fumbles": "0.0",
        "FumblesLost": "0.0"
    },
    "1971": {
        "Tm": "DEN",
        "Pos": "TE",
        "Age": "27.0",
        "G": "14.0",
        "GS": "12.0",
        "Rec": "27.0",
        "PassingYds": "0.0",
        "PassingTD": "0.0",
        "PassingAtt": "0.0",
        "RushingYds": "71.0",
        "RushingTD": "0.0",
        "RushingAtt": "7.0",
        "ReceivingYds": "382.0",
        "ReceivingTD": "1.0",
        "FantasyPoints": "76.3",
        "Int": "0.0",
        "Fumbles": "1.0",
        "FumblesLost": "0.0"
    },
    "1972": {
        "Tm": "DEN",
        "Pos": "TE",
        "Age": "28.0",
        "G": "14.0",
        "GS": "14.0",
        "Rec": "25.0",
        "PassingYds": "0.0",
        "PassingTD": "0.0",
        "PassingAtt": "0.0",
        "RushingYds": "-15.0",
        "RushingTD": "0.0",
        "RushingAtt": "3.0",
        "ReceivingYds": "393.0",
        "ReceivingTD": "3.0",
        "FantasyPoints": "78.8",
        "Int": "0.0",
        "Fumbles": "1.0",
        "FumblesLost": "0.0"
    },
    "1973": {
        "Tm": "DEN",
        "Pos": "TE",
        "Age": "29.0",
        "G": "11.0",
        "GS": "0.0",
        "Rec": "5.0",
        "PassingYds": "0.0",
        "PassingTD": "0.0",
        "PassingAtt": "0.0",
        "RushingYds": "-9.0",
        "RushingTD": "0.0",
        "RushingAtt": "1.0",
        "ReceivingYds": "65.0",
        "ReceivingTD": "0.0",
        "FantasyPoints": "8.6",
        "Int": "0.0",
        "Fumbles": "1.0",
        "FumblesLost": "0.0"
    },
    "1974": {
        "Tm": "DEN",
        "Pos": "0",
        "Age": "30.0",
        "G": "13.0",
        "GS": "1.0",
        "Rec": "0.0",
        "PassingYds": "0.0",
        "PassingTD": "0.0",
        "PassingAtt": "0.0",
        "RushingYds": "0.0",
        "RushingTD": "0.0",
        "RushingAtt": "0.0",
        "ReceivingYds": "0.0",
        "ReceivingTD": "0.0",
        "FantasyPoints": "0.0",
        "Int": "0.0",
        "Fumbles": "0.0",
        "FumblesLost": "0.0"
    },
    "1975": {
        "Tm": "KAN",
        "Pos": "TE",
        "Age": "31.0",
        "G": "14.0",
        "GS": "14.0",
        "Rec": "24.0",
        "PassingYds": "0.0",
        "PassingTD": "0.0",
        "PassingAtt": "0.0",
        "RushingYds": "0.0",
        "RushingTD": "0.0",
        "RushingAtt": "0.0",
        "ReceivingYds": "314.0",
        "ReceivingTD": "3.0",
        "FantasyPoints": "71.4",
        "Int": "0.0",
        "Fumbles": "1.0",
        "FumblesLost": "0.0"
    },
    "1976": {
        "Tm": "KAN",
        "Pos": "TE",
        "Age": "32.0",
        "G": "10.0",
        "GS": "9.0",
        "Rec": "18.0",
        "PassingYds": "0.0",
        "PassingTD": "0.0",
        "PassingAtt": "0.0",
        "RushingYds": "0.0",
        "RushingTD": "0.0",
        "RushingAtt": "0.0",
        "ReceivingYds": "269.0",
        "ReceivingTD": "3.0",
        "FantasyPoints": "62.9",
        "Int": "0.0",
        "Fumbles": "0.0",
        "FumblesLost": "0.0"
    }
}