{
    "Pos": "TE",
    "2019": {
        "Tm": "BUF",
        "Pos": "TE",
        "Age": "23.0",
        "G": "15.0",
        "GS": "11.0",
        "Rec": "28.0",
        "PassingYds": "0.0",
        "PassingTD": "0.0",
        "PassingAtt": "0.0",
        "RushingYds": "9.0",
        "RushingTD": "0.0",
        "RushingAtt": "1.0",
        "ReceivingYds": "388.0",
        "ReceivingTD": "2.0",
        "FantasyPoints": "79.7",
        "Int": "0.0",
        "Fumbles": "0.0",
        "FumblesLost": "0.0"
    },
    "2020": {
        "Tm": "BUF",
        "Pos": "TE",
        "Age": "24",
        "G": "12",
        "GS": "7",
        "Rec": "24",
        "PassingYds": "0",
        "PassingTD": "0",
        "PassingAtt": "0",
        "RushingYds": "0",
        "RushingTD": "0",
        "RushingAtt": "0",
        "ReceivingYds": "288",
        "ReceivingTD": "3",
        "FantasyPoints": "43",
        "Int": "0",
        "Fumbles": "2",
        "FumblesLost": "2"
    }
}