{
    "Pos": "TE",
    "1974": {
        "Tm": "MIN",
        "Pos": "TE",
        "Age": "23.0",
        "G": "14.0",
        "GS": "0.0",
        "Rec": "4.0",
        "PassingYds": "0.0",
        "PassingTD": "0.0",
        "PassingAtt": "0.0",
        "RushingYds": "0.0",
        "RushingTD": "0.0",
        "RushingAtt": "0.0",
        "ReceivingYds": "26.0",
        "ReceivingTD": "1.0",
        "FantasyPoints": "12.6",
        "Int": "0.0",
        "Fumbles": "0.0",
        "FumblesLost": "0.0"
    },
    "1975": {
        "Tm": "MIN",
        "Pos": "TE",
        "Age": "24.0",
        "G": "14.0",
        "GS": "1.0",
        "Rec": "6.0",
        "PassingYds": "0.0",
        "PassingTD": "0.0",
        "PassingAtt": "0.0",
        "RushingYds": "0.0",
        "RushingTD": "0.0",
        "RushingAtt": "0.0",
        "ReceivingYds": "68.0",
        "ReceivingTD": "0.0",
        "FantasyPoints": "12.8",
        "Int": "0.0",
        "Fumbles": "0.0",
        "FumblesLost": "0.0"
    },
    "1976": {
        "Tm": "MIN",
        "Pos": "TE",
        "Age": "25.0",
        "G": "14.0",
        "GS": "0.0",
        "Rec": "3.0",
        "PassingYds": "0.0",
        "PassingTD": "0.0",
        "PassingAtt": "0.0",
        "RushingYds": "0.0",
        "RushingTD": "0.0",
        "RushingAtt": "0.0",
        "ReceivingYds": "33.0",
        "ReceivingTD": "0.0",
        "FantasyPoints": "6.3",
        "Int": "0.0",
        "Fumbles": "0.0",
        "FumblesLost": "0.0"
    },
    "1977": {
        "Tm": "MIN",
        "Pos": "TE",
        "Age": "26.0",
        "G": "14.0",
        "GS": "0.0",
        "Rec": "1.0",
        "PassingYds": "0.0",
        "PassingTD": "0.0",
        "PassingAtt": "0.0",
        "RushingYds": "0.0",
        "RushingTD": "0.0",
        "RushingAtt": "0.0",
        "ReceivingYds": "14.0",
        "ReceivingTD": "0.0",
        "FantasyPoints": "2.4",
        "Int": "0.0",
        "Fumbles": "0.0",
        "FumblesLost": "0.0"
    },
    "1978": {
        "Tm": "MIN",
        "Pos": "TE",
        "Age": "27.0",
        "G": "16.0",
        "GS": "0.0",
        "Rec": "4.0",
        "PassingYds": "0.0",
        "PassingTD": "0.0",
        "PassingAtt": "0.0",
        "RushingYds": "0.0",
        "RushingTD": "0.0",
        "RushingAtt": "0.0",
        "ReceivingYds": "31.0",
        "ReceivingTD": "0.0",
        "FantasyPoints": "7.1",
        "Int": "0.0",
        "Fumbles": "0.0",
        "FumblesLost": "0.0"
    }
}