{
    "Pos": "RB",
    "2008": {
        "Tm": "OAK",
        "Pos": "RB",
        "Age": "21.0",
        "G": "13.0",
        "GS": "5.0",
        "Rec": "29.0",
        "PassingYds": "0.0",
        "PassingTD": "0.0",
        "PassingAtt": "0.0",
        "RushingYds": "499.0",
        "RushingTD": "4.0",
        "RushingAtt": "113.0",
        "ReceivingYds": "285.0",
        "ReceivingTD": "0.0",
        "FantasyPoints": "129.4",
        "Int": "0.0",
        "Fumbles": "3.0",
        "FumblesLost": "1.0"
    },
    "2009": {
        "Tm": "OAK",
        "Pos": "RB",
        "Age": "22.0",
        "G": "12.0",
        "GS": "7.0",
        "Rec": "21.0",
        "PassingYds": "0.0",
        "PassingTD": "0.0",
        "PassingAtt": "0.0",
        "RushingYds": "357.0",
        "RushingTD": "1.0",
        "RushingAtt": "104.0",
        "ReceivingYds": "245.0",
        "ReceivingTD": "0.0",
        "FantasyPoints": "81.2",
        "Int": "0.0",
        "Fumbles": "5.0",
        "FumblesLost": "3.0"
    },
    "2010": {
        "Tm": "OAK",
        "Pos": "RB",
        "Age": "23.0",
        "G": "13.0",
        "GS": "13.0",
        "Rec": "47.0",
        "PassingYds": "0.0",
        "PassingTD": "0.0",
        "PassingAtt": "1.0",
        "RushingYds": "1157.0",
        "RushingTD": "7.0",
        "RushingAtt": "223.0",
        "ReceivingYds": "507.0",
        "ReceivingTD": "3.0",
        "FantasyPoints": "267.4",
        "Int": "0.0",
        "Fumbles": "4.0",
        "FumblesLost": "3.0"
    },
    "2011": {
        "Tm": "OAK",
        "Pos": "RB",
        "Age": "24.0",
        "G": "7.0",
        "GS": "7.0",
        "Rec": "19.0",
        "PassingYds": "0.0",
        "PassingTD": "0.0",
        "PassingAtt": "0.0",
        "RushingYds": "614.0",
        "RushingTD": "4.0",
        "RushingAtt": "113.0",
        "ReceivingYds": "154.0",
        "ReceivingTD": "1.0",
        "FantasyPoints": "123.8",
        "Int": "0.0",
        "Fumbles": "1.0",
        "FumblesLost": "1.0"
    },
    "2012": {
        "Tm": "OAK",
        "Pos": "RB",
        "Age": "25.0",
        "G": "12.0",
        "GS": "12.0",
        "Rec": "42.0",
        "PassingYds": "0.0",
        "PassingTD": "0.0",
        "PassingAtt": "0.0",
        "RushingYds": "707.0",
        "RushingTD": "2.0",
        "RushingAtt": "216.0",
        "ReceivingYds": "258.0",
        "ReceivingTD": "1.0",
        "FantasyPoints": "152.5",
        "Int": "0.0",
        "Fumbles": "2.0",
        "FumblesLost": "2.0"
    },
    "2013": {
        "Tm": "OAK",
        "Pos": "RB",
        "Age": "26.0",
        "G": "10.0",
        "GS": "7.0",
        "Rec": "17.0",
        "PassingYds": "16.0",
        "PassingTD": "1.0",
        "PassingAtt": "1.0",
        "RushingYds": "379.0",
        "RushingTD": "5.0",
        "RushingAtt": "114.0",
        "ReceivingYds": "108.0",
        "ReceivingTD": "0.0",
        "FantasyPoints": "98.34",
        "Int": "0.0",
        "Fumbles": "1.0",
        "FumblesLost": "1.0"
    },
    "2014": {
        "Tm": "OAK",
        "Pos": "RB",
        "Age": "27.0",
        "G": "16.0",
        "GS": "12.0",
        "Rec": "36.0",
        "PassingYds": "0.0",
        "PassingTD": "0.0",
        "PassingAtt": "1.0",
        "RushingYds": "534.0",
        "RushingTD": "2.0",
        "RushingAtt": "155.0",
        "ReceivingYds": "212.0",
        "ReceivingTD": "0.0",
        "FantasyPoints": "120.6",
        "Int": "0.0",
        "Fumbles": "1.0",
        "FumblesLost": "1.0"
    },
    "2015": {
        "Tm": "DAL",
        "Pos": "RB",
        "Age": "28.0",
        "G": "16.0",
        "GS": "10.0",
        "Rec": "40.0",
        "PassingYds": "0.0",
        "PassingTD": "0.0",
        "PassingAtt": "1.0",
        "RushingYds": "1089.0",
        "RushingTD": "3.0",
        "RushingAtt": "239.0",
        "ReceivingYds": "328.0",
        "ReceivingTD": "0.0",
        "FantasyPoints": "193.7",
        "Int": "0.0",
        "Fumbles": "3.0",
        "FumblesLost": "3.0"
    },
    "2016": {
        "Tm": "DAL",
        "Pos": "RB",
        "Age": "29.0",
        "G": "3.0",
        "GS": "2.0",
        "Rec": "3.0",
        "PassingYds": "0.0",
        "PassingTD": "0.0",
        "PassingAtt": "0.0",
        "RushingYds": "87.0",
        "RushingTD": "0.0",
        "RushingAtt": "24.0",
        "ReceivingYds": "17.0",
        "ReceivingTD": "0.0",
        "FantasyPoints": "13.4",
        "Int": "0.0",
        "Fumbles": "0.0",
        "FumblesLost": "0.0"
    },
    "2017": {
        "Tm": "DAL",
        "Pos": "RB",
        "Age": "30.0",
        "G": "1.0",
        "GS": "0.0",
        "Rec": "0.0",
        "PassingYds": "0.0",
        "PassingTD": "0.0",
        "PassingAtt": "0.0",
        "RushingYds": "-2.0",
        "RushingTD": "0.0",
        "RushingAtt": "1.0",
        "ReceivingYds": "0.0",
        "ReceivingTD": "0.0",
        "FantasyPoints": "-0.2",
        "Int": "0.0",
        "Fumbles": "0.0",
        "FumblesLost": "0.0"
    }
}