{
    "Pos": "RB",
    "2012": {
        "Tm": "NYG",
        "Pos": "RB",
        "Age": "21.0",
        "G": "16.0",
        "GS": "2.0",
        "Rec": "4.0",
        "PassingYds": "0.0",
        "PassingTD": "0.0",
        "PassingAtt": "0.0",
        "RushingYds": "358.0",
        "RushingTD": "4.0",
        "RushingAtt": "71.0",
        "ReceivingYds": "34.0",
        "ReceivingTD": "1.0",
        "FantasyPoints": "71.19999999999997",
        "Int": "0.0",
        "Fumbles": "1.0",
        "FumblesLost": "1.0"
    },
    "2013": {
        "Tm": "NYG",
        "Pos": "RB",
        "Age": "22.0",
        "G": "5.0",
        "GS": "4.0",
        "Rec": "2.0",
        "PassingYds": "0.0",
        "PassingTD": "0.0",
        "PassingAtt": "0.0",
        "RushingYds": "146.0",
        "RushingTD": "1.0",
        "RushingAtt": "44.0",
        "ReceivingYds": "8.0",
        "ReceivingTD": "0.0",
        "FantasyPoints": "19.4",
        "Int": "0.0",
        "Fumbles": "2.0",
        "FumblesLost": "2.0"
    },
    "2014": {
        "Tm": "NYG",
        "Pos": "0",
        "Age": "23.0",
        "G": "0.0",
        "GS": "0.0",
        "Rec": "0.0",
        "PassingYds": "0.0",
        "PassingTD": "0.0",
        "PassingAtt": "0.0",
        "RushingYds": "0.0",
        "RushingTD": "0.0",
        "RushingAtt": "0.0",
        "ReceivingYds": "0.0",
        "ReceivingTD": "0.0",
        "FantasyPoints": "0.0",
        "Int": "0.0",
        "Fumbles": "0.0",
        "FumblesLost": "0.0"
    }
}