{
    "Pos": "RB",
    "2008": {
        "Tm": "DAL",
        "Pos": "RB",
        "Age": "21.0",
        "G": "6.0",
        "GS": "0.0",
        "Rec": "2.0",
        "PassingYds": "0.0",
        "PassingTD": "0.0",
        "PassingAtt": "0.0",
        "RushingYds": "266.0",
        "RushingTD": "3.0",
        "RushingAtt": "30.0",
        "ReceivingYds": "10.0",
        "ReceivingTD": "0.0",
        "FantasyPoints": "47.6",
        "Int": "0.0",
        "Fumbles": "0.0",
        "FumblesLost": "0.0"
    },
    "2009": {
        "Tm": "DAL",
        "Pos": "RB",
        "Age": "22.0",
        "G": "14.0",
        "GS": "1.0",
        "Rec": "19.0",
        "PassingYds": "0.0",
        "PassingTD": "0.0",
        "PassingAtt": "0.0",
        "RushingYds": "685.0",
        "RushingTD": "3.0",
        "RushingAtt": "116.0",
        "ReceivingYds": "119.0",
        "ReceivingTD": "0.0",
        "FantasyPoints": "113.4",
        "Int": "0.0",
        "Fumbles": "3.0",
        "FumblesLost": "2.0"
    },
    "2010": {
        "Tm": "DAL",
        "Pos": "RB",
        "Age": "23.0",
        "G": "16.0",
        "GS": "7.0",
        "Rec": "48.0",
        "PassingYds": "0.0",
        "PassingTD": "0.0",
        "PassingAtt": "0.0",
        "RushingYds": "800.0",
        "RushingTD": "1.0",
        "RushingAtt": "185.0",
        "ReceivingYds": "450.0",
        "ReceivingTD": "1.0",
        "FantasyPoints": "183.0",
        "Int": "0.0",
        "Fumbles": "2.0",
        "FumblesLost": "1.0"
    },
    "2011": {
        "Tm": "DAL",
        "Pos": "RB",
        "Age": "24.0",
        "G": "12.0",
        "GS": "8.0",
        "Rec": "33.0",
        "PassingYds": "0.0",
        "PassingTD": "0.0",
        "PassingAtt": "0.0",
        "RushingYds": "575.0",
        "RushingTD": "1.0",
        "RushingAtt": "127.0",
        "ReceivingYds": "221.0",
        "ReceivingTD": "0.0",
        "FantasyPoints": "114.6",
        "Int": "0.0",
        "Fumbles": "5.0",
        "FumblesLost": "2.0"
    },
    "2012": {
        "Tm": "DAL",
        "Pos": "RB",
        "Age": "25.0",
        "G": "16.0",
        "GS": "7.0",
        "Rec": "25.0",
        "PassingYds": "0.0",
        "PassingTD": "0.0",
        "PassingAtt": "0.0",
        "RushingYds": "402.0",
        "RushingTD": "3.0",
        "RushingAtt": "111.0",
        "ReceivingYds": "262.0",
        "ReceivingTD": "2.0",
        "FantasyPoints": "117.4",
        "Int": "0.0",
        "Fumbles": "2.0",
        "FumblesLost": "2.0"
    },
    "2013": {
        "Tm": "PIT",
        "Pos": "RB",
        "Age": "26.0",
        "G": "16.0",
        "GS": "2.0",
        "Rec": "9.0",
        "PassingYds": "0.0",
        "PassingTD": "0.0",
        "PassingAtt": "0.0",
        "RushingYds": "184.0",
        "RushingTD": "0.0",
        "RushingAtt": "48.0",
        "ReceivingYds": "63.0",
        "ReceivingTD": "0.0",
        "FantasyPoints": "31.70000000000001",
        "Int": "0.0",
        "Fumbles": "1.0",
        "FumblesLost": "1.0"
    }
}