{
    "Pos": "RB",
    "1972": {
        "Tm": "RAM",
        "Pos": "RB",
        "Age": "22.0",
        "G": "14.0",
        "GS": "7.0",
        "Rec": "29.0",
        "PassingYds": "0.0",
        "PassingTD": "0.0",
        "PassingAtt": "0.0",
        "RushingYds": "581.0",
        "RushingTD": "5.0",
        "RushingAtt": "123.0",
        "ReceivingYds": "331.0",
        "ReceivingTD": "1.0",
        "FantasyPoints": "148.2",
        "Int": "0.0",
        "Fumbles": "4.0",
        "FumblesLost": "0.0"
    },
    "1973": {
        "Tm": "RAM",
        "Pos": "RB",
        "Age": "23.0",
        "G": "14.0",
        "GS": "14.0",
        "Rec": "19.0",
        "PassingYds": "0.0",
        "PassingTD": "0.0",
        "PassingAtt": "0.0",
        "RushingYds": "854.0",
        "RushingTD": "4.0",
        "RushingAtt": "206.0",
        "ReceivingYds": "267.0",
        "ReceivingTD": "1.0",
        "FantasyPoints": "153.10000000000002",
        "Int": "0.0",
        "Fumbles": "4.0",
        "FumblesLost": "0.0"
    },
    "1974": {
        "Tm": "RAM",
        "Pos": "RB",
        "Age": "24.0",
        "G": "13.0",
        "GS": "13.0",
        "Rec": "20.0",
        "PassingYds": "0.0",
        "PassingTD": "0.0",
        "PassingAtt": "0.0",
        "RushingYds": "419.0",
        "RushingTD": "2.0",
        "RushingAtt": "127.0",
        "ReceivingYds": "175.0",
        "ReceivingTD": "0.0",
        "FantasyPoints": "83.4",
        "Int": "0.0",
        "Fumbles": "4.0",
        "FumblesLost": "0.0"
    },
    "1975": {
        "Tm": "RAM",
        "Pos": "RB",
        "Age": "25.0",
        "G": "13.0",
        "GS": "10.0",
        "Rec": "14.0",
        "PassingYds": "0.0",
        "PassingTD": "0.0",
        "PassingAtt": "0.0",
        "RushingYds": "457.0",
        "RushingTD": "3.0",
        "RushingAtt": "116.0",
        "ReceivingYds": "208.0",
        "ReceivingTD": "0.0",
        "FantasyPoints": "94.5",
        "Int": "0.0",
        "Fumbles": "2.0",
        "FumblesLost": "0.0"
    },
    "1976": {
        "Tm": "RAM",
        "Pos": "RB",
        "Age": "26.0",
        "G": "14.0",
        "GS": "0.0",
        "Rec": "6.0",
        "PassingYds": "0.0",
        "PassingTD": "0.0",
        "PassingAtt": "0.0",
        "RushingYds": "155.0",
        "RushingTD": "2.0",
        "RushingAtt": "42.0",
        "ReceivingYds": "33.0",
        "ReceivingTD": "0.0",
        "FantasyPoints": "30.799999999999997",
        "Int": "0.0",
        "Fumbles": "3.0",
        "FumblesLost": "0.0"
    }
}