{
    "Pos": "RB",
    "1991": {
        "Tm": "KAN",
        "Pos": "RB",
        "Age": "25.0",
        "G": "2.0",
        "GS": "0.0",
        "Rec": "2.0",
        "PassingYds": "0.0",
        "PassingTD": "0.0",
        "PassingAtt": "0.0",
        "RushingYds": "0.0",
        "RushingTD": "0.0",
        "RushingAtt": "0.0",
        "ReceivingYds": "30.0",
        "ReceivingTD": "0.0",
        "FantasyPoints": "5.0",
        "Int": "0.0",
        "Fumbles": "0.0",
        "FumblesLost": "0.0"
    },
    "1992": {
        "Tm": "KAN",
        "Pos": "RB",
        "Age": "26.0",
        "G": "11.0",
        "GS": "2.0",
        "Rec": "5.0",
        "PassingYds": "0.0",
        "PassingTD": "0.0",
        "PassingAtt": "0.0",
        "RushingYds": "1.0",
        "RushingTD": "0.0",
        "RushingAtt": "1.0",
        "ReceivingYds": "65.0",
        "ReceivingTD": "0.0",
        "FantasyPoints": "9.6",
        "Int": "0.0",
        "Fumbles": "1.0",
        "FumblesLost": "0.0"
    },
    "1993": {
        "Tm": "KAN",
        "Pos": "RB",
        "Age": "27.0",
        "G": "16.0",
        "GS": "13.0",
        "Rec": "40.0",
        "PassingYds": "0.0",
        "PassingTD": "0.0",
        "PassingAtt": "0.0",
        "RushingYds": "291.0",
        "RushingTD": "0.0",
        "RushingAtt": "75.0",
        "ReceivingYds": "326.0",
        "ReceivingTD": "1.0",
        "FantasyPoints": "105.7",
        "Int": "0.0",
        "Fumbles": "1.0",
        "FumblesLost": "0.0"
    },
    "1994": {
        "Tm": "KAN",
        "Pos": "RB",
        "Age": "28.0",
        "G": "16.0",
        "GS": "13.0",
        "Rec": "67.0",
        "PassingYds": "0.0",
        "PassingTD": "0.0",
        "PassingAtt": "0.0",
        "RushingYds": "231.0",
        "RushingTD": "2.0",
        "RushingAtt": "62.0",
        "ReceivingYds": "525.0",
        "ReceivingTD": "1.0",
        "FantasyPoints": "160.6",
        "Int": "0.0",
        "Fumbles": "1.0",
        "FumblesLost": "0.0"
    },
    "1995": {
        "Tm": "KAN",
        "Pos": "RB",
        "Age": "29.0",
        "G": "16.0",
        "GS": "13.0",
        "Rec": "55.0",
        "PassingYds": "0.0",
        "PassingTD": "0.0",
        "PassingAtt": "0.0",
        "RushingYds": "398.0",
        "RushingTD": "2.0",
        "RushingAtt": "58.0",
        "ReceivingYds": "349.0",
        "ReceivingTD": "1.0",
        "FantasyPoints": "145.7",
        "Int": "0.0",
        "Fumbles": "1.0",
        "FumblesLost": "1.0"
    },
    "1996": {
        "Tm": "KAN",
        "Pos": "RB",
        "Age": "30.0",
        "G": "16.0",
        "GS": "15.0",
        "Rec": "60.0",
        "PassingYds": "0.0",
        "PassingTD": "0.0",
        "PassingAtt": "0.0",
        "RushingYds": "201.0",
        "RushingTD": "2.0",
        "RushingAtt": "54.0",
        "ReceivingYds": "529.0",
        "ReceivingTD": "2.0",
        "FantasyPoints": "157.0",
        "Int": "0.0",
        "Fumbles": "0.0",
        "FumblesLost": "0.0"
    },
    "1997": {
        "Tm": "KAN",
        "Pos": "RB",
        "Age": "31.0",
        "G": "15.0",
        "GS": "14.0",
        "Rec": "59.0",
        "PassingYds": "0.0",
        "PassingTD": "0.0",
        "PassingAtt": "0.0",
        "RushingYds": "397.0",
        "RushingTD": "0.0",
        "RushingAtt": "79.0",
        "ReceivingYds": "453.0",
        "ReceivingTD": "2.0",
        "FantasyPoints": "156.0",
        "Int": "0.0",
        "Fumbles": "3.0",
        "FumblesLost": "0.0"
    },
    "1998": {
        "Tm": "KAN",
        "Pos": "RB",
        "Age": "32.0",
        "G": "16.0",
        "GS": "15.0",
        "Rec": "64.0",
        "PassingYds": "0.0",
        "PassingTD": "0.0",
        "PassingAtt": "0.0",
        "RushingYds": "230.0",
        "RushingTD": "1.0",
        "RushingAtt": "58.0",
        "ReceivingYds": "462.0",
        "ReceivingTD": "2.0",
        "FantasyPoints": "149.2",
        "Int": "0.0",
        "Fumbles": "6.0",
        "FumblesLost": "1.0"
    },
    "1999": {
        "Tm": "KAN",
        "Pos": "RB",
        "Age": "33.0",
        "G": "2.0",
        "GS": "2.0",
        "Rec": "2.0",
        "PassingYds": "0.0",
        "PassingTD": "0.0",
        "PassingAtt": "0.0",
        "RushingYds": "181.0",
        "RushingTD": "0.0",
        "RushingAtt": "32.0",
        "ReceivingYds": "14.0",
        "ReceivingTD": "0.0",
        "FantasyPoints": "21.5",
        "Int": "0.0",
        "Fumbles": "1.0",
        "FumblesLost": "0.0"
    },
    "2000": {
        "Tm": "KAN",
        "Pos": "RB",
        "Age": "34.0",
        "G": "15.0",
        "GS": "7.0",
        "Rec": "15.0",
        "PassingYds": "0.0",
        "PassingTD": "0.0",
        "PassingAtt": "0.0",
        "RushingYds": "331.0",
        "RushingTD": "2.0",
        "RushingAtt": "76.0",
        "ReceivingYds": "76.0",
        "ReceivingTD": "0.0",
        "FantasyPoints": "67.7",
        "Int": "0.0",
        "Fumbles": "1.0",
        "FumblesLost": "0.0"
    }
}