{
    "Pos": "RB",
    "2016": {
        "Tm": "WAS",
        "Pos": "RB",
        "Age": "24.0",
        "G": "15.0",
        "GS": "9.0",
        "Rec": "12.0",
        "PassingYds": "0.0",
        "PassingTD": "0.0",
        "PassingAtt": "0.0",
        "RushingYds": "704.0",
        "RushingTD": "6.0",
        "RushingAtt": "168.0",
        "ReceivingYds": "82.0",
        "ReceivingTD": "1.0",
        "FantasyPoints": "132.60000000000002",
        "Int": "0.0",
        "Fumbles": "0.0",
        "FumblesLost": "0.0"
    },
    "2017": {
        "Tm": "WAS",
        "Pos": "RB",
        "Age": "25.0",
        "G": "7.0",
        "GS": "7.0",
        "Rec": "4.0",
        "PassingYds": "0.0",
        "PassingTD": "0.0",
        "PassingAtt": "0.0",
        "RushingYds": "194.0",
        "RushingTD": "3.0",
        "RushingAtt": "62.0",
        "ReceivingYds": "18.0",
        "ReceivingTD": "0.0",
        "FantasyPoints": "43.2",
        "Int": "0.0",
        "Fumbles": "0.0",
        "FumblesLost": "0.0"
    },
    "2018": {
        "Tm": "WAS",
        "Pos": "RB",
        "Age": "26.0",
        "G": "2.0",
        "GS": "0.0",
        "Rec": "0.0",
        "PassingYds": "0.0",
        "PassingTD": "0.0",
        "PassingAtt": "0.0",
        "RushingYds": "8.0",
        "RushingTD": "0.0",
        "RushingAtt": "4.0",
        "ReceivingYds": "0.0",
        "ReceivingTD": "0.0",
        "FantasyPoints": "0.8",
        "Int": "0.0",
        "Fumbles": "0.0",
        "FumblesLost": "0.0"
    }
}