{
    "Pos": "WR",
    "1971": {
        "Tm": "SDG",
        "Pos": "WR",
        "Age": "23.0",
        "G": "10.0",
        "GS": "10.0",
        "Rec": "41.0",
        "PassingYds": "0.0",
        "PassingTD": "0.0",
        "PassingAtt": "0.0",
        "RushingYds": "77.0",
        "RushingTD": "0.0",
        "RushingAtt": "5.0",
        "ReceivingYds": "609.0",
        "ReceivingTD": "4.0",
        "FantasyPoints": "129.6",
        "Int": "0.0",
        "Fumbles": "2.0",
        "FumblesLost": "0.0"
    },
    "1972": {
        "Tm": "DAL",
        "Pos": "WR",
        "Age": "24.0",
        "G": "12.0",
        "GS": "7.0",
        "Rec": "18.0",
        "PassingYds": "0.0",
        "PassingTD": "0.0",
        "PassingAtt": "0.0",
        "RushingYds": "0.0",
        "RushingTD": "0.0",
        "RushingAtt": "0.0",
        "ReceivingYds": "298.0",
        "ReceivingTD": "1.0",
        "FantasyPoints": "53.8",
        "Int": "0.0",
        "Fumbles": "0.0",
        "FumblesLost": "0.0"
    },
    "1973": {
        "Tm": "HOU",
        "Pos": "WR",
        "Age": "25.0",
        "G": "14.0",
        "GS": "14.0",
        "Rec": "43.0",
        "PassingYds": "0.0",
        "PassingTD": "0.0",
        "PassingAtt": "0.0",
        "RushingYds": "0.0",
        "RushingTD": "0.0",
        "RushingAtt": "0.0",
        "ReceivingYds": "581.0",
        "ReceivingTD": "1.0",
        "FantasyPoints": "105.1",
        "Int": "0.0",
        "Fumbles": "1.0",
        "FumblesLost": "0.0"
    },
    "1974": {
        "Tm": "HOU",
        "Pos": "WR",
        "Age": "26.0",
        "G": "14.0",
        "GS": "12.0",
        "Rec": "20.0",
        "PassingYds": "0.0",
        "PassingTD": "0.0",
        "PassingAtt": "0.0",
        "RushingYds": "0.0",
        "RushingTD": "0.0",
        "RushingAtt": "0.0",
        "ReceivingYds": "330.0",
        "ReceivingTD": "1.0",
        "FantasyPoints": "59.0",
        "Int": "0.0",
        "Fumbles": "0.0",
        "FumblesLost": "0.0"
    },
    "1975": {
        "Tm": "HOU",
        "Pos": "WR",
        "Age": "27.0",
        "G": "10.0",
        "GS": "0.0",
        "Rec": "1.0",
        "PassingYds": "0.0",
        "PassingTD": "0.0",
        "PassingAtt": "0.0",
        "RushingYds": "0.0",
        "RushingTD": "0.0",
        "RushingAtt": "0.0",
        "ReceivingYds": "8.0",
        "ReceivingTD": "0.0",
        "FantasyPoints": "1.8",
        "Int": "0.0",
        "Fumbles": "0.0",
        "FumblesLost": "0.0"
    }
}