{
    "Pos": "WR",
    "1970": {
        "Tm": "PHI",
        "Pos": "WR",
        "Age": "24.0",
        "G": "14.0",
        "GS": "12.0",
        "Rec": "41.0",
        "PassingYds": "0.0",
        "PassingTD": "0.0",
        "PassingAtt": "0.0",
        "RushingYds": "-5.0",
        "RushingTD": "0.0",
        "RushingAtt": "1.0",
        "ReceivingYds": "613.0",
        "ReceivingTD": "5.0",
        "FantasyPoints": "131.8",
        "Int": "0.0",
        "Fumbles": "0.0",
        "FumblesLost": "0.0"
    },
    "1971": {
        "Tm": "PHI",
        "Pos": "WR",
        "Age": "25.0",
        "G": "14.0",
        "GS": "12.0",
        "Rec": "47.0",
        "PassingYds": "0.0",
        "PassingTD": "0.0",
        "PassingAtt": "0.0",
        "RushingYds": "41.0",
        "RushingTD": "0.0",
        "RushingAtt": "5.0",
        "ReceivingYds": "716.0",
        "ReceivingTD": "3.0",
        "FantasyPoints": "138.7",
        "Int": "0.0",
        "Fumbles": "1.0",
        "FumblesLost": "0.0"
    },
    "1972": {
        "Tm": "PHI",
        "Pos": "WR",
        "Age": "26.0",
        "G": "14.0",
        "GS": "14.0",
        "Rec": "62.0",
        "PassingYds": "0.0",
        "PassingTD": "0.0",
        "PassingAtt": "0.0",
        "RushingYds": "76.0",
        "RushingTD": "0.0",
        "RushingAtt": "9.0",
        "ReceivingYds": "1048.0",
        "ReceivingTD": "4.0",
        "FantasyPoints": "194.4",
        "Int": "0.0",
        "Fumbles": "2.0",
        "FumblesLost": "0.0"
    },
    "1973": {
        "Tm": "RAM",
        "Pos": "WR",
        "Age": "27.0",
        "G": "14.0",
        "GS": "14.0",
        "Rec": "40.0",
        "PassingYds": "0.0",
        "PassingTD": "0.0",
        "PassingAtt": "0.0",
        "RushingYds": "-8.0",
        "RushingTD": "0.0",
        "RushingAtt": "2.0",
        "ReceivingYds": "874.0",
        "ReceivingTD": "13.0",
        "FantasyPoints": "204.6",
        "Int": "0.0",
        "Fumbles": "0.0",
        "FumblesLost": "0.0"
    },
    "1974": {
        "Tm": "RAM",
        "Pos": "WR",
        "Age": "28.0",
        "G": "14.0",
        "GS": "14.0",
        "Rec": "30.0",
        "PassingYds": "0.0",
        "PassingTD": "0.0",
        "PassingAtt": "0.0",
        "RushingYds": "4.0",
        "RushingTD": "0.0",
        "RushingAtt": "1.0",
        "ReceivingYds": "514.0",
        "ReceivingTD": "5.0",
        "FantasyPoints": "111.80000000000001",
        "Int": "0.0",
        "Fumbles": "0.0",
        "FumblesLost": "0.0"
    },
    "1975": {
        "Tm": "RAM",
        "Pos": "WR",
        "Age": "29.0",
        "G": "14.0",
        "GS": "14.0",
        "Rec": "43.0",
        "PassingYds": "0.0",
        "PassingTD": "0.0",
        "PassingAtt": "0.0",
        "RushingYds": "0.0",
        "RushingTD": "0.0",
        "RushingAtt": "0.0",
        "ReceivingYds": "786.0",
        "ReceivingTD": "7.0",
        "FantasyPoints": "161.6",
        "Int": "0.0",
        "Fumbles": "1.0",
        "FumblesLost": "0.0"
    },
    "1976": {
        "Tm": "RAM",
        "Pos": "WR",
        "Age": "30.0",
        "G": "14.0",
        "GS": "14.0",
        "Rec": "39.0",
        "PassingYds": "0.0",
        "PassingTD": "0.0",
        "PassingAtt": "0.0",
        "RushingYds": "15.0",
        "RushingTD": "0.0",
        "RushingAtt": "1.0",
        "ReceivingYds": "751.0",
        "ReceivingTD": "5.0",
        "FantasyPoints": "143.6",
        "Int": "0.0",
        "Fumbles": "1.0",
        "FumblesLost": "0.0"
    },
    "1977": {
        "Tm": "RAM",
        "Pos": "WR",
        "Age": "31.0",
        "G": "14.0",
        "GS": "14.0",
        "Rec": "48.0",
        "PassingYds": "0.0",
        "PassingTD": "0.0",
        "PassingAtt": "0.0",
        "RushingYds": "6.0",
        "RushingTD": "0.0",
        "RushingAtt": "1.0",
        "ReceivingYds": "666.0",
        "ReceivingTD": "6.0",
        "FantasyPoints": "151.2",
        "Int": "0.0",
        "Fumbles": "0.0",
        "FumblesLost": "0.0"
    },
    "1978": {
        "Tm": "NWE",
        "Pos": "WR",
        "Age": "32.0",
        "G": "16.0",
        "GS": "13.0",
        "Rec": "37.0",
        "PassingYds": "0.0",
        "PassingTD": "0.0",
        "PassingAtt": "0.0",
        "RushingYds": "7.0",
        "RushingTD": "0.0",
        "RushingAtt": "1.0",
        "ReceivingYds": "743.0",
        "ReceivingTD": "6.0",
        "FantasyPoints": "148.0",
        "Int": "0.0",
        "Fumbles": "0.0",
        "FumblesLost": "0.0"
    },
    "1979": {
        "Tm": "NWE",
        "Pos": "WR",
        "Age": "33.0",
        "G": "16.0",
        "GS": "16.0",
        "Rec": "45.0",
        "PassingYds": "0.0",
        "PassingTD": "0.0",
        "PassingAtt": "1.0",
        "RushingYds": "12.0",
        "RushingTD": "0.0",
        "RushingAtt": "3.0",
        "ReceivingYds": "1013.0",
        "ReceivingTD": "7.0",
        "FantasyPoints": "189.5",
        "Int": "0.0",
        "Fumbles": "0.0",
        "FumblesLost": "0.0"
    },
    "1980": {
        "Tm": "NWE",
        "Pos": "WR",
        "Age": "34.0",
        "G": "16.0",
        "GS": "15.0",
        "Rec": "35.0",
        "PassingYds": "35.0",
        "PassingTD": "0.0",
        "PassingAtt": "2.0",
        "RushingYds": "37.0",
        "RushingTD": "0.0",
        "RushingAtt": "5.0",
        "ReceivingYds": "737.0",
        "ReceivingTD": "5.0",
        "FantasyPoints": "143.79999999999998",
        "Int": "0.0",
        "Fumbles": "0.0",
        "FumblesLost": "0.0"
    },
    "1981": {
        "Tm": "NWE",
        "Pos": "WR",
        "Age": "35.0",
        "G": "16.0",
        "GS": "15.0",
        "Rec": "39.0",
        "PassingYds": "0.0",
        "PassingTD": "0.0",
        "PassingAtt": "1.0",
        "RushingYds": "-14.0",
        "RushingTD": "0.0",
        "RushingAtt": "2.0",
        "ReceivingYds": "669.0",
        "ReceivingTD": "0.0",
        "FantasyPoints": "102.5",
        "Int": "0.0",
        "Fumbles": "1.0",
        "FumblesLost": "0.0"
    },
    "1982": {
        "Tm": "MIN",
        "Pos": "0",
        "Age": "36.0",
        "G": "1.0",
        "GS": "0.0",
        "Rec": "0.0",
        "PassingYds": "0.0",
        "PassingTD": "0.0",
        "PassingAtt": "0.0",
        "RushingYds": "0.0",
        "RushingTD": "0.0",
        "RushingAtt": "0.0",
        "ReceivingYds": "0.0",
        "ReceivingTD": "0.0",
        "FantasyPoints": "0.0",
        "Int": "0.0",
        "Fumbles": "0.0",
        "FumblesLost": "0.0"
    },
    "1983": {
        "Tm": "SEA",
        "Pos": "WR",
        "Age": "37.0",
        "G": "15.0",
        "GS": "6.0",
        "Rec": "8.0",
        "PassingYds": "0.0",
        "PassingTD": "0.0",
        "PassingAtt": "0.0",
        "RushingYds": "0.0",
        "RushingTD": "0.0",
        "RushingAtt": "0.0",
        "ReceivingYds": "126.0",
        "ReceivingTD": "1.0",
        "FantasyPoints": "24.6",
        "Int": "0.0",
        "Fumbles": "1.0",
        "FumblesLost": "0.0"
    }
}