{
    "Pos": "WR",
    "2010": {
        "Tm": "SDG",
        "Pos": "WR",
        "Age": "23.0",
        "G": "10.0",
        "GS": "0.0",
        "Rec": "13.0",
        "PassingYds": "0.0",
        "PassingTD": "0.0",
        "PassingAtt": "0.0",
        "RushingYds": "0.0",
        "RushingTD": "0.0",
        "RushingAtt": "0.0",
        "ReceivingYds": "262.0",
        "ReceivingTD": "2.0",
        "FantasyPoints": "51.2",
        "Int": "0.0",
        "Fumbles": "0.0",
        "FumblesLost": "0.0"
    },
    "2011": {
        "Tm": "CAR",
        "Pos": "WR",
        "Age": "24.0",
        "G": "14.0",
        "GS": "0.0",
        "Rec": "1.0",
        "PassingYds": "0.0",
        "PassingTD": "0.0",
        "PassingAtt": "0.0",
        "RushingYds": "0.0",
        "RushingTD": "0.0",
        "RushingAtt": "0.0",
        "ReceivingYds": "4.0",
        "ReceivingTD": "0.0",
        "FantasyPoints": "1.4",
        "Int": "0.0",
        "Fumbles": "0.0",
        "FumblesLost": "0.0"
    },
    "2012": {
        "Tm": "SDG",
        "Pos": "WR",
        "Age": "25.0",
        "G": "3.0",
        "GS": "1.0",
        "Rec": "3.0",
        "PassingYds": "0.0",
        "PassingTD": "0.0",
        "PassingAtt": "0.0",
        "RushingYds": "0.0",
        "RushingTD": "0.0",
        "RushingAtt": "0.0",
        "ReceivingYds": "45.0",
        "ReceivingTD": "0.0",
        "FantasyPoints": "7.5",
        "Int": "0.0",
        "Fumbles": "0.0",
        "FumblesLost": "0.0"
    },
    "2013": {
        "Tm": "SDG",
        "Pos": "WR",
        "Age": "26.0",
        "G": "14.0",
        "GS": "0.0",
        "Rec": "3.0",
        "PassingYds": "0.0",
        "PassingTD": "0.0",
        "PassingAtt": "0.0",
        "RushingYds": "0.0",
        "RushingTD": "0.0",
        "RushingAtt": "0.0",
        "ReceivingYds": "64.0",
        "ReceivingTD": "1.0",
        "FantasyPoints": "15.4",
        "Int": "0.0",
        "Fumbles": "0.0",
        "FumblesLost": "0.0"
    },
    "2014": {
        "Tm": "SDG",
        "Pos": "WR",
        "Age": "27.0",
        "G": "16.0",
        "GS": "1.0",
        "Rec": "4.0",
        "PassingYds": "0.0",
        "PassingTD": "0.0",
        "PassingAtt": "0.0",
        "RushingYds": "0.0",
        "RushingTD": "0.0",
        "RushingAtt": "0.0",
        "ReceivingYds": "45.0",
        "ReceivingTD": "0.0",
        "FantasyPoints": "8.5",
        "Int": "0.0",
        "Fumbles": "0.0",
        "FumblesLost": "0.0"
    },
    "2015": {
        "Tm": "PHI",
        "Pos": "WR",
        "Age": "28.0",
        "G": "13.0",
        "GS": "0.0",
        "Rec": "1.0",
        "PassingYds": "0.0",
        "PassingTD": "0.0",
        "PassingAtt": "0.0",
        "RushingYds": "0.0",
        "RushingTD": "0.0",
        "RushingAtt": "0.0",
        "ReceivingYds": "4.0",
        "ReceivingTD": "0.0",
        "FantasyPoints": "1.4",
        "Int": "0.0",
        "Fumbles": "0.0",
        "FumblesLost": "0.0"
    }
}