{
    "Pos": "QB",
    "2004": {
        "Tm": "SDG",
        "Pos": "QB",
        "Age": "23.0",
        "G": "2.0",
        "GS": "0.0",
        "Rec": "0.0",
        "PassingYds": "33.0",
        "PassingTD": "1.0",
        "PassingAtt": "8.0",
        "RushingYds": "-5.0",
        "RushingTD": "0.0",
        "RushingAtt": "4.0",
        "ReceivingYds": "0.0",
        "ReceivingTD": "0.0",
        "FantasyPoints": "4.82",
        "Int": "0.0",
        "Fumbles": "1.0",
        "FumblesLost": "0.0"
    },
    "2005": {
        "Tm": "SDG",
        "Pos": "QB",
        "Age": "24.0",
        "G": "2.0",
        "GS": "0.0",
        "Rec": "0.0",
        "PassingYds": "115.0",
        "PassingTD": "0.0",
        "PassingAtt": "22.0",
        "RushingYds": "-1.0",
        "RushingTD": "0.0",
        "RushingAtt": "1.0",
        "ReceivingYds": "0.0",
        "ReceivingTD": "0.0",
        "FantasyPoints": "2.5",
        "Int": "1.0",
        "Fumbles": "2.0",
        "FumblesLost": "0.0"
    },
    "2006": {
        "Tm": "SDG",
        "Pos": "QB",
        "Age": "25.0",
        "G": "16.0",
        "GS": "16.0",
        "Rec": "0.0",
        "PassingYds": "3388.0",
        "PassingTD": "22.0",
        "PassingAtt": "460.0",
        "RushingYds": "49.0",
        "RushingTD": "0.0",
        "RushingAtt": "48.0",
        "ReceivingYds": "0.0",
        "ReceivingTD": "0.0",
        "FantasyPoints": "206.42",
        "Int": "9.0",
        "Fumbles": "8.0",
        "FumblesLost": "2.0"
    },
    "2007": {
        "Tm": "SDG",
        "Pos": "QB",
        "Age": "26.0",
        "G": "16.0",
        "GS": "16.0",
        "Rec": "0.0",
        "PassingYds": "3152.0",
        "PassingTD": "21.0",
        "PassingAtt": "460.0",
        "RushingYds": "33.0",
        "RushingTD": "1.0",
        "RushingAtt": "29.0",
        "ReceivingYds": "0.0",
        "ReceivingTD": "0.0",
        "FantasyPoints": "177.38",
        "Int": "15.0",
        "Fumbles": "11.0",
        "FumblesLost": "6.0"
    },
    "2008": {
        "Tm": "SDG",
        "Pos": "QB",
        "Age": "27.0",
        "G": "16.0",
        "GS": "16.0",
        "Rec": "0.0",
        "PassingYds": "4009.0",
        "PassingTD": "34.0",
        "PassingAtt": "478.0",
        "RushingYds": "84.0",
        "RushingTD": "0.0",
        "RushingAtt": "31.0",
        "ReceivingYds": "0.0",
        "ReceivingTD": "0.0",
        "FantasyPoints": "274.76",
        "Int": "11.0",
        "Fumbles": "8.0",
        "FumblesLost": "4.0"
    },
    "2009": {
        "Tm": "SDG",
        "Pos": "QB",
        "Age": "28.0",
        "G": "16.0",
        "GS": "16.0",
        "Rec": "0.0",
        "PassingYds": "4254.0",
        "PassingTD": "28.0",
        "PassingAtt": "486.0",
        "RushingYds": "50.0",
        "RushingTD": "1.0",
        "RushingAtt": "26.0",
        "ReceivingYds": "0.0",
        "ReceivingTD": "0.0",
        "FantasyPoints": "269.16",
        "Int": "9.0",
        "Fumbles": "6.0",
        "FumblesLost": "3.0"
    },
    "2010": {
        "Tm": "SDG",
        "Pos": "QB",
        "Age": "29.0",
        "G": "16.0",
        "GS": "16.0",
        "Rec": "0.0",
        "PassingYds": "4710.0",
        "PassingTD": "30.0",
        "PassingAtt": "541.0",
        "RushingYds": "52.0",
        "RushingTD": "0.0",
        "RushingAtt": "29.0",
        "ReceivingYds": "0.0",
        "ReceivingTD": "0.0",
        "FantasyPoints": "279.6",
        "Int": "13.0",
        "Fumbles": "7.0",
        "FumblesLost": "4.0"
    },
    "2011": {
        "Tm": "SDG",
        "Pos": "QB",
        "Age": "30.0",
        "G": "16.0",
        "GS": "16.0",
        "Rec": "0.0",
        "PassingYds": "4624.0",
        "PassingTD": "27.0",
        "PassingAtt": "582.0",
        "RushingYds": "36.0",
        "RushingTD": "1.0",
        "RushingAtt": "26.0",
        "ReceivingYds": "0.0",
        "ReceivingTD": "0.0",
        "FantasyPoints": "252.5600000000001",
        "Int": "20.0",
        "Fumbles": "9.0",
        "FumblesLost": "5.0"
    },
    "2012": {
        "Tm": "SDG",
        "Pos": "QB",
        "Age": "31.0",
        "G": "16.0",
        "GS": "16.0",
        "Rec": "0.0",
        "PassingYds": "3606.0",
        "PassingTD": "26.0",
        "PassingAtt": "527.0",
        "RushingYds": "40.0",
        "RushingTD": "0.0",
        "RushingAtt": "27.0",
        "ReceivingYds": "0.0",
        "ReceivingTD": "0.0",
        "FantasyPoints": "208.24",
        "Int": "15.0",
        "Fumbles": "15.0",
        "FumblesLost": "7.0"
    },
    "2013": {
        "Tm": "SDG",
        "Pos": "QB",
        "Age": "32.0",
        "G": "16.0",
        "GS": "16.0",
        "Rec": "0.0",
        "PassingYds": "4478.0",
        "PassingTD": "32.0",
        "PassingAtt": "544.0",
        "RushingYds": "72.0",
        "RushingTD": "0.0",
        "RushingAtt": "28.0",
        "ReceivingYds": "-9.0",
        "ReceivingTD": "0.0",
        "FantasyPoints": "287.42",
        "Int": "11.0",
        "Fumbles": "3.0",
        "FumblesLost": "2.0"
    },
    "2014": {
        "Tm": "SDG",
        "Pos": "QB",
        "Age": "33.0",
        "G": "16.0",
        "GS": "16.0",
        "Rec": "0.0",
        "PassingYds": "4286.0",
        "PassingTD": "31.0",
        "PassingAtt": "570.0",
        "RushingYds": "102.0",
        "RushingTD": "0.0",
        "RushingAtt": "37.0",
        "ReceivingYds": "0.0",
        "ReceivingTD": "0.0",
        "FantasyPoints": "265.64",
        "Int": "18.0",
        "Fumbles": "8.0",
        "FumblesLost": "2.0"
    },
    "2015": {
        "Tm": "SDG",
        "Pos": "QB",
        "Age": "34.0",
        "G": "16.0",
        "GS": "16.0",
        "Rec": "0.0",
        "PassingYds": "4792.0",
        "PassingTD": "29.0",
        "PassingAtt": "661.0",
        "RushingYds": "28.0",
        "RushingTD": "0.0",
        "RushingAtt": "17.0",
        "ReceivingYds": "0.0",
        "ReceivingTD": "0.0",
        "FantasyPoints": "280.48",
        "Int": "13.0",
        "Fumbles": "4.0",
        "FumblesLost": "2.0"
    },
    "2016": {
        "Tm": "SDG",
        "Pos": "QB",
        "Age": "35.0",
        "G": "16.0",
        "GS": "16.0",
        "Rec": "0.0",
        "PassingYds": "4386.0",
        "PassingTD": "33.0",
        "PassingAtt": "578.0",
        "RushingYds": "35.0",
        "RushingTD": "0.0",
        "RushingAtt": "14.0",
        "ReceivingYds": "0.0",
        "ReceivingTD": "0.0",
        "FantasyPoints": "258.94",
        "Int": "21.0",
        "Fumbles": "9.0",
        "FumblesLost": "5.0"
    },
    "2017": {
        "Tm": "LAC",
        "Pos": "QB",
        "Age": "36.0",
        "G": "16.0",
        "GS": "16.0",
        "Rec": "0.0",
        "PassingYds": "4515.0",
        "PassingTD": "28.0",
        "PassingAtt": "575.0",
        "RushingYds": "-2.0",
        "RushingTD": "0.0",
        "RushingAtt": "18.0",
        "ReceivingYds": "0.0",
        "ReceivingTD": "0.0",
        "FantasyPoints": "270.40000000000003",
        "Int": "10.0",
        "Fumbles": "8.0",
        "FumblesLost": "1.0"
    },
    "2018": {
        "Tm": "LAC",
        "Pos": "QB",
        "Age": "37.0",
        "G": "16.0",
        "GS": "16.0",
        "Rec": "0.0",
        "PassingYds": "4308.0",
        "PassingTD": "32.0",
        "PassingAtt": "508.0",
        "RushingYds": "7.0",
        "RushingTD": "0.0",
        "RushingAtt": "18.0",
        "ReceivingYds": "0.0",
        "ReceivingTD": "0.0",
        "FantasyPoints": "275.02",
        "Int": "12.0",
        "Fumbles": "2.0",
        "FumblesLost": "1.0"
    },
    "2019": {
        "Tm": "LAC",
        "Pos": "QB",
        "Age": "38.0",
        "G": "16.0",
        "GS": "16.0",
        "Rec": "0.0",
        "PassingYds": "4615.0",
        "PassingTD": "23.0",
        "PassingAtt": "591.0",
        "RushingYds": "29.0",
        "RushingTD": "0.0",
        "RushingAtt": "12.0",
        "ReceivingYds": "0.0",
        "ReceivingTD": "0.0",
        "FantasyPoints": "233.50000000000003",
        "Int": "20.0",
        "Fumbles": "8.0",
        "FumblesLost": "3.0"
    },
    "2020": {
        "Tm": "IND",
        "Pos": "QB",
        "Age": "39",
        "G": "16",
        "GS": "16",
        "Rec": "0",
        "PassingYds": "4169",
        "PassingTD": "24",
        "PassingAtt": "543",
        "RushingYds": "-8",
        "RushingTD": "0",
        "RushingAtt": "18",
        "ReceivingYds": "0",
        "ReceivingTD": "0",
        "FantasyPoints": "240",
        "Int": "11",
        "Fumbles": "2",
        "FumblesLost": "1"
    }
}